{
  "title": "Recent Posts",
  "items": [
    {
      "title": "AWS Gateway API Controller",
      "permalink": "/kubernetes/gatewayapi"
    },
    {
      "title": "Kubernetes Headless Service",
      "permalink": "/kubernetes/headless-service/"
    },
    {
      "title": "ExternalDNS",
      "permalink": "/kubernetes/externaldns/"
    },
    {
      "title": "Multus on Kind cluster",
      "permalink": "/kubernetes/multus-on-kind/"
    },
    {
      "title": "파드 Readiness & Probe",
      "permalink": "/kubernetes/readinessandprobe/"
    }
  ]
}